[
    {
        "homeTeam": "C",
        "awayTeam": "D",
        "homeScore": 0,
        "awayScore": 0,
        "inProgress": false,
        "id": 1
    },
    {
        "homeTeam": "A",
        "awayTeam": "B",
        "homeScore": 0,
        "awayScore": 0,
        "inProgress": false,
        "id": 2
    },
    {
        "homeTeam": "E",
        "awayTeam": "F",
        "homeScore": 0,
        "awayScore": 0,
        "inProgress": false,
        "id": 3
    },
    {
        "homeTeam": "A",
        "awayTeam": "P",
        "homeScore": 0,
        "awayScore": 0,
        "inProgress": false,
        "id": 4
    },
    {
        "homeTeam": "A",
        "awayTeam": "B",
        "homeScore": 0,
        "awayScore": 0,
        "inProgress": false,
        "id": 5
    }
]